{
    "government": "MAHARASTRA GOVERNMENT",
    "document_no": "12345XYZ",
    "date_of_issue": "15-Feb-2025",
    "owner": {
        "name": "John Doe",
        "address": "123 Main Street, City, Country"
    },
    "property_details": {
        "location": "Block 10, Plot No. 567, Springfield",
        "land_area": "5000 sq. meters",
        "survey_no": "789XYZ",
        "type_of_land": "Residential"
    },
    "encumbrances": "No outstanding loans or legal claims.",
    "transaction_history": {
        "previous_owner": "Jane Smith",
        "date_of_transfer": "10-Jan-2024"
    }
}